nrp_invenio_client/__init__.py
nrp_invenio_client/base.py
nrp_invenio_client/errors.py
nrp_invenio_client/files.py
nrp_invenio_client/info.py
nrp_invenio_client/records.py
nrp_invenio_client/requests.py
nrp_invenio_client/search.py
nrp_invenio_client/utils.py
nrp_invenio_client/cli/__init__.py
nrp_invenio_client/cli/alias.py
nrp_invenio_client/cli/base.py
nrp_invenio_client/cli/commands.py
nrp_invenio_client/cli/describe.py
nrp_invenio_client/cli/files.py
nrp_invenio_client/cli/output.py
nrp_invenio_client/cli/record.py
nrp_invenio_client/cli/requests.py
nrp_invenio_client/cli/search.py
nrp_invenio_client/cli/set.py
nrp_invenio_client/cli/utils.py
nrp_invenio_client/config/__init__.py
nrp_invenio_client/config/config.py
nrp_invenio_client/config/repository_config.py
nrp_invenio_client-0.3.1.dist-info/METADATA
nrp_invenio_client-0.3.1.dist-info/WHEEL
nrp_invenio_client-0.3.1.dist-info/entry_points.txt
nrp_invenio_client-0.3.1.dist-info/top_level.txt
nrp_invenio_client-0.3.1.dist-info/RECORD
